vqr/__init__.py
vqr/__version__.py
vqr/api.py
vqr/coverage.py
vqr/cvqf.py
vqr/models.py
vqr/plot.py
vqr/utils.py
vqr/solvers/__init__.py
vqr/solvers/base.py
vqr/solvers/cvx.py
vqr/solvers/pot.py
vqr/solvers/regularized_lse.py
vqr-1.0.0.dist-info/LICENSE
vqr-1.0.0.dist-info/METADATA
vqr-1.0.0.dist-info/WHEEL
vqr-1.0.0.dist-info/top_level.txt
vqr-1.0.0.dist-info/RECORD
