Metadata-Version: 2.1
Name: vqr
Version: 1.0.0
Summary: Vector Quantile Regression
Home-page: https://github.com/vistalab-technion/vqr
Author: Aviv A. Rosenberg & Sanketh Vedula
Author-email: avivr@cs.technion.ac.il
License: proprietary
Platform: any
Classifier: Development Status :: 4 - Beta
Classifier: Programming Language :: Python
Requires-Python: >=3.8
License-File: LICENSE
Requires-Dist: cvxpy
Requires-Dist: numpy
Requires-Dist: POT
Requires-Dist: scikit-learn
Requires-Dist: scipy
Requires-Dist: torch
Requires-Dist: tqdm
Provides-Extra: testing
Requires-Dist: pytest ; extra == 'testing'
Requires-Dist: pytest-cov ; extra == 'testing'
